xasp/__init__.py
xasp/commands.py
xasp/contexts.py
xasp/entities.py
xasp/main.py
xasp/queries.py
xasp/transformers.py
xasp/utils.py
xasp-0.8.3.dist-info/METADATA
xasp-0.8.3.dist-info/WHEEL
xasp-0.8.3.dist-info/RECORD
